Workbook

Sheet term one 2026
B1: SI No. | C1: First Name | D1: Middle Name | E1: Last Name | F1: Class Code | G1: Payment Code | H1: Guardian Phone | I1: fees due | J1: outstanding | K1: amount paid | L1: balance | M1: category | N1: colour category | O1: debt carried forward
B2: 1 | C2: Aleem | D2: Galugali | E2: Afan | F2: ELEPHANT | G2: 1010521012 | I2: 290000 | K2: =100000+100000+90000 -> 290000 | L2: =I2+J2-K2 -> 0
B3: 2 | C3: Mugambwa | D3: tyrone Tendo | E3: Mukasa | F3: ELEPHANT | G3: 1010607442 | I3: 290000 | K3: =200000+90000 -> 290000 | L3: =I3+J3-K3 -> 0
B4: 3 | C4: Nikky | D4: Nansubuga | F4: ELEPHANT | G4: 1010668240 | I4: 200000 | K4: =100000+100000 -> 200000 | L4: =I4+J4-K4 -> 0
B5: 4 | C5: Nabatanzi | D5: Bint Hamis | E5: Hannah | F5: ELEPHANT | G5: 1010680309 | I5: 270000 | K5: =150000+120000 -> 270000 | L5: =I5+J5-K5 -> 0
B6: 5 | C6: Sempela | D6: Paul | E6: Troy | F6: ELEPHANT | I6: =290000+300000 -> 590000 | K6: =590000 -> 590000 | L6: =I6+J6-K6 -> 0
B7: 6 | C7: Ruth | D7: Mirab | F7: ELEPHANT | I7: =200000 -> 200000 | K7: =150000+50000 -> 200000 | L7: =I7+J7-K7 -> 0
B8: 7 | C8: Nimurungi | D8: Alvin | E8: Sserugo | F8: ELEPHANT | I8: 80000 | K8: =80000 -> 80000 | L8: =I8+J8-K8 -> 0
B9: 8 | C9: Nalubega | D9: Samantha | E9: Zion | F9: ELEPHANT | I9: 80000 | K9: =40000 -> 40000 | L9: =I9+J9-K9 -> 40000
B10: 9 | C10: Nanyonga | D10: Pretty | E10: kiwanuka | F10: ELEPHANT | I10: 200000 | K10: =200000 -> 200000 | L10: =I10+J10-K10 -> 0
B11: 10 | C11: Adeke | D11: Dinah | F11: ELEPHANT | I11: 290000 | K11: =290000 -> 290000 | L11: =I11+J11-K11 -> 0
B12: 11 | C12: Namutebi | D12: Shukran | F12: ELEPHANT | I12: =260000 -> 260000 | K12: =100000+80000+60000+20000 -> 260000 | L12: =I12+J12-K12 -> 0 | M12: discount
B13: 12 | C13: Mukisa | D13: Daniel | F13: ELEPHANT | I13: =290000+250000 -> 540000 | K13: =540000 -> 540000 | L13: =I13+J13-K13 -> 0
A14: 7 | B14: 13 | C14: Wesonga | D14: Emmanuel | F14: ZEBRA | I14: =260000+100000 -> 360000 | K14: =100000+200000 -> 300000 | L14: =I14+J14-K14 -> 60000 | M14: vau user | N14: 260000
B15: 14 | C15: Aafruuz | D15: Mutambuli | E15: Mansoor | F15: ELEPHANT | I15: =100000 -> 100000 | K15: =50000+50000 -> 100000 | L15: =I15+J15-K15 -> 0
B16: 15 | C16: Mali | D16: Gracious | F16: ELEPHANT | I16: 80000 | K16: =80000 -> 80000 | L16: =I16+J16-K16 -> 0
B17: =1+B16 -> 16 | F17: ELEPHANT | L17: =I17+J17-K17 -> 0
B18: =1+B17 -> 17 | F18: ELEPHANT | L18: =I18+J18-K18 -> 0
B19: =1+B18 -> 18 | F19: ELEPHANT | L19: =I19+J19-K19 -> 0
B20: =1+B19 -> 19 | F20: ELEPHANT | L20: =I20+J20-K20 -> 0
B21: =1+B20 -> 20 | F21: ELEPHANT | L21: =I21+J21-K21 -> 0
D22: ZEBRA | I22: 0 | L22: =I22+J22-K22 -> 0
A23: 2 | B23: 1 | C23: Nansubuga | E23: Shuquran | F23: ZEBRA | G23: 1008799582 | I23: =290000 -> 290000 | K23: =150000+50000+50000+40000 -> 290000 | L23: =I23+J23-K23 -> 0
A24: 3 | B24: 2 | C24: Wamala | E24: Abdu | F24: ZEBRA | G24: 1008807850 | I24: =290000 -> 290000 | K24: =100000+59000+70000+60000 -> 289000 | L24: =I24+J24-K24 -> 1000
A25: 6 | B25: 3 | C25: Namwori | E25: Grace | F25: ZEBRA | G25: 1008878539 | I25: ='[1]1st term 2025'!J8 -> 80000 | K25: =80000 -> 80000 | L25: =I25+J25-K25 -> 0 | M25: teachers child
A26: 8 | B26: 4 | C26: Bakish | D26: Shakirah | E26: Muhammed | F26: ZEBRA | I26: ='[1]1st term 2025'!J10 -> 260000 | K26: =100000+160000 -> 260000 | L26: =I26+J26-K26 -> 0
A27: 9 | B27: 5 | C27: ivana | D27: Namutebi | F27: ZEBRA | I27: ='[1]1st term 2025'!J11 -> 80000 | K27: =50000+30000 -> 80000 | L27: =I27+J27-K27 -> 0 | M27: cook
A28: 11 | B28: 6 | C28: Ssenyondo | D28: Biden | E28: kakooza jovan | F28: ZEBRA | G28: 1009022251 | I28: =290000 -> 290000 | K28: =100000+100000 -> 200000 | L28: =I28+J28-K28 -> 90000
A29: 12 | B29: 7 | C29: Nakitende | D29: mercy | E29: Elizabeth | F29: ZEBRA | G29: 1008940427 | I29: =290000 -> 290000 | K29: =150000+50000+60000+30000+100000 -> 390000 | L29: =I29+J29-K29 -> -100000
A30: 15 | B30: 8 | C30: Muwanguzi | D30: Lael | E30: victor | F30: ZEBRA | G30: 1009102896 | I30: ='[1]1st term 2025'!J17+30000 -> 290000 | K30: =200000+90000 -> 290000 | L30: =I30+J30-K30 -> 0 | N30: 180000
A31: 17 | B31: 9 | C31: Gabriell | D31: Ayerango | E31: Grace | F31: ZEBRA | G31: 1009426740 | I31: =290000+50000 -> 340000 | K31: =120000+100000+120000 -> 340000 | L31: =I31+J31-K31 -> 0 | M31: reported in march
A32: 18 | B32: 10 | C32: Mulwanyi | E32: Chrizestom | F32: ZEBRA | G32: 1008793531 | I32: =230000 -> 230000 | K32: =50000+50000+50000 -> 150000 | L32: =I32+J32-K32 -> 80000 | M32: harmony atuheire 50000
B33: 11 | C33: Kaleb | D33: Myles | E33: Kolya | F33: ZEBRA | G33: 1009836293 | I33: =260000+30000 -> 290000 | K33: =270000+20000 -> 290000 | L33: =I33+J33-K33 -> 0
B34: 12 | C34: Princess | D34: Ayinebyona | E34: Nakato | F34: ZEBRA | I34: =260000+30000 -> 290000 | K34: =20000+20000+10000+10000+10000+20000+20000+15000+20000 -> 145000 | L34: =I34+J34-K34 -> 145000
B35: 13 | C35: Lauren | D35: Asio | E35: Malaika | F35: ZEBRA | I35: =290000+50000 -> 340000 | K35: =160000+180000 -> 340000 | L35: =I35+J35-K35 -> 0
L36: =I36+J36-K36 -> 0
D37: LION | I37: ='[1]1st term 2025'!J23 -> 0 | L37: =I37+J37-K37 -> 0
A38: 19 | B38: 1 | C38: Nakigozi | D38: Brovia | E38: Martha | F38: LION | G38: 1006914417 | I38: ='[1]1st term 2025'!J24 -> 255000 | K38: =200000+55000+70000 -> 325000 | L38: =I38+J38-K38 -> -70000 | M38: f
A39: 20 | B39: 2 | C39: Ssemakula | D39: Joseph | E39: Asher | F39: LION | G39: 1006914745 | I39: ='[1]1st term 2025'!J25 -> 80000 | K39: =80000 -> 80000 | L39: =I39+J39-K39 -> 0 | M39: f
A40: 22 | B40: 3 | C40: Kristian | D40: Pendo | E40: Ogola | F40: LION | G40: 1007134587 | I40: ='[1]1st term 2025'!J27 -> 260000 | K40: =260000 -> 260000 | L40: =I40+J40-K40 -> 0 | M40: f | N40: =L41+L44+#REF!+L45+#REF!+L49+#REF! -> #REF!
A41: 23 | B41: 4 | C41: Nakyeyune | D41: Hamnah | E41: Sarah | F41: LION | G41: 1007092280 | I41: ='[1]1st term 2025'!J28 -> 260000 | K41: =100000+80000 -> 180000 | L41: =I41+J41-K41 -> 80000 | M41: f
A42: 24 | B42: 5 | C42: Ekisula ebweru | E42: salim | F42: LION | G42: 1007044996 | I42: ='[1]1st term 2025'!J29 -> 290000 | K42: =290000 -> 290000 | L42: =I42+J42-K42 -> 0 | M42: f
A43: 25 | B43: 6 | C43: Babirye | D43: Miracle | E43: Victoria | F43: LION | I43: 260000 | L43: =I43+J43-K43 -> 260000 | M43: f | N43: yellow =iccsp
A44: 27 | B44: 7 | C44: Ganiima | D44: Nakkuni | E44: Ramsha | F44: LION | I44: ='[1]1st term 2025'!J32 -> 260000 | K44: =100000+160000 -> 260000 | L44: =I44+J44-K44 -> 0 | M44: f
A45: 29 | B45: 8 | C45: Kiyimba | E45: Joram | F45: LION | G45: 1005580041 | I45: ='[1]1st term 2025'!J34 -> 230000 | K45: =230000 -> 230000 | L45: =I45+J45-K45 -> 0 | M45: nakyanzi f | N45: 274000
A46: 30 | B46: 9 | C46: Mukisa | E46: Sharom | F46: LION | G46: 1007986138 | I46: 0 | L46: =I46+J46-K46 -> 0
A47: 32 | B47: 10 | C47: Saka | E47: Raymond | F47: LION | G47: 1007991074 | I47: ='[1]1st term 2025'!J37+30000 -> 290000 | K47: =50000+100000+50000+25000 -> 225000 | L47: =I47+J47-K47 -> 65000
A48: 33 | B48: 11 | C48: Suhairah | E48: Isah | F48: LION | G48: 1008057858 | I48: ='[1]1st term 2025'!J38+30000 -> 290000 | K48: =100000+100000 -> 200000 | L48: =I48+J48-K48 -> 90000 | N48: =SUM(L38+#REF!+L40+L41+L42+#REF!+#REF!+L44+#REF!+L45+#REF!+L47+L48) -> #REF!
A49: 35 | B49: 12 | C49: Nakanda | E49: mourisha | F49: LION | G49: 1008793043 | I49: ='[1]1st term 2025'!J40+100000 -> 370000 | L49: =I49+J49-K49 -> 370000 | M49: discount lunch | N49: 80000
A50: 36 | B50: 13 | C50: Mubiru | E50: Fahim | F50: LION | G50: 1008799658 | I50: ='[1]1st term 2025'!J41 -> 260000 | K50: =150000+50000+60000 -> 260000 | L50: =I50+J50-K50 -> 0
A51: 38 | B51: 14 | C51: Hossana | D51: Nakiberu | E51: Abigail | F51: LION | I51: ='[1]1st term 2025'!J43 -> 260000 | K51: =100000+100000+60000 -> 260000 | L51: =I51+J51-K51 -> 0
A52: 40 | B52: 15 | C52: mudoola | D52: Travis | F52: LION | I52: ='[1]1st term 2025'!J45 -> 80000 | K52: =80000 -> 80000 | L52: =I52+J52-K52 -> 0
B53: 16 | C53: Ninsiima | D53: Dyna | F53: LION | G53: 1009792957 | I53: =290000+200000 -> 490000 | K53: =210000+200000+80000 -> 490000 | L53: =I53+J53-K53 -> 0 | M53: van user
B54: 17 | C54: Namuganyi | D54: kellen | F54: LION | I54: =260000+30000 -> 290000 | K54: =100000+100000+70000+50000 -> 320000 | L54: =I54+J54-K54 -> -30000 | N54: 80000
B55: 18 | C55: Nakibuuka | D55: Mary | F55: LION | I55: =260000+30000 -> 290000 | K55: =90000+10000+100000 -> 200000 | L55: =I55+J55-K55 -> 90000
B56: 19 | C56: Mirembe | D56: Lois | F56: LION | I56: 80000 | K56: =80000 -> 80000 | L56: =I56+J56-K56 -> 0
F57: PRIMARY ONE
A58: 42 | B58: 1 | C58: Victor | E58: Mugisha | F58: P.1 | G58: 1004598780 | H58: 705362439 | I58: =310000 -> 310000 | K58: =115000 -> 115000 | L58: =I58+J58-K58 -> 195000 | M58: staff(eva nakalembe) f | N58: 390000
A59: 43 | B59: 2 | C59: Emmanuella | D59: Lubega | E59: Namboozo | F59: P.1 | G59: 1004970591 | H59: 706082006 | I59: 100000 | K59: =100000 -> 100000 | L59: =I59+J59-K59 -> 0 | M59: plus lunch f
A60: 44 | B60: 3 | C60: Mirembe | E60: Zuri | F60: P.1 | G60: 1004702849 | H60: 789426721 | I60: 0 | L60: =I60+J60-K60 -> 0 | M60: plus lunch f
A61: 45 | B61: 4 | C61: Jeredin | D61: Kibumba | E61: Bitege | F61: P.1 | G61: 1005019546 | H61: 759659001 | I61: =310000 -> 310000 | K61: =150000+50000+50000 -> 250000 | L61: =I61+J61-K61 -> 60000 | M61: f
A62: 47 | B62: 5 | C62: Haitham | E62: Kyeyune | F62: P.1 | G62: 1006568232 | I62: =310000 -> 310000 | K62: =100000+100000 -> 200000 | L62: =I62+J62-K62 -> 110000 | M62: lunch also inclusive at this amount f
A63: 48 | B63: 6 | C63: kawalya | E63: hormony | F63: P.1 | G63: 1006597691 | I63: =300000 -> 300000 | K63: =50000+100000+150000 -> 300000 | L63: =I63+J63-K63 -> 0 | M63: plus lunch f | N63: =L58+#REF! -> #REF!
A64: 49 | B64: 7 | C64: Lwanga | D64: Destiny | E64: Adrian | F64: P.1 | G64: 1006613640 | I64: 0 | L64: =I64+J64-K64 -> 0 | M64: f | N64: red= otm
A65: 50 | B65: 8 | C65: Jeremiah | E65: Mukisa | F65: P.1 | I65: 0 | L65: =I65+J65-K65 -> 0 | M65: f
A66: 51 | B66: 9 | C66: Gift | E66: nakiwala | F66: P.1 | I66: 0 | L66: =I66+J66-K66 -> 0 | M66: f
A67: 54 | B67: 10 | C67: Ethan | D67: Prosper | E67: Kaweesa | F67: P.1 | G67: 1007073672 | I67: =310000+100000 -> 410000 | K67: =150000+150000 -> 300000 | L67: =I67+J67-K67 -> 110000 | M67: van user
A68: 55 | B68: 11 | C68: Kizza | D68: Brian | E68: Bumpenje Prosper | F68: P.1 | G68: 1006973917 | I68: 0 | L68: =I68+J68-K68 -> 0 | M68: f | N68: blue =GA
A69: 56 | B69: 12 | C69: Nakasujja | D69: Ivy | E69: Catherine | F69: P.1 | G69: 1007985992 | I69: =310000 -> 310000 | K69: =150000+160000 -> 310000 | L69: =I69+J69-K69 -> 0
A70: 57 | B70: 13 | C70: Mukisa | E70: Nathaniel | F70: P.1 | G70: 1007986167 | I70: 0 | L70: =I70+J70-K70 -> 0
A71: 58 | B71: 14 | C71: Crystal | D71: Havah | E71: Aturinda | F71: P.1 | G71: 1008016084 | I71: =310000+150000 -> 460000 | K71: =350000+110000 -> 460000 | L71: =I71+J71-K71 -> 0 | N71: =SUM(L58+L61+#REF!+L62+L63+#REF!+#REF!+#REF!+L67+L69+#REF!+L71+L72) -> #REF!
A72: 59 | B72: 15 | C72: Kajjubi | D72: Alkham | F72: P.1 | G72: 1008448676 | I72: =310000 -> 310000 | K72: =60000+100000+80000 -> 240000 | L72: =I72+J72-K72 -> 70000
A73: 60 | B73: 16 | C73: Precious | D73: Maali | E73: evelyne | F73: P.1 | I73: ='[1]1st term 2025'!J67 -> 80000 | K73: =80000 -> 80000 | L73: =I73+J73-K73 -> 0
A74: 61 | B74: 17 | C74: Serena | D74: Achadu | E74: Barrika | F74: P.1 | G74: 1008697299 | I74: =310000 -> 310000 | K74: =100000+100000+110000 -> 310000 | L74: =I74+J74-K74 -> 0 | M74: ekwap and humphrey
A75: 62 | B75: 18 | C75: Latifa | D75: Nambuya | E75: Malika | F75: P.1 | I75: ='[1]1st term 2025'!J69 -> 500000 | K75: =500000 -> 500000 | L75: =I75+J75-K75 -> 0 | M75: discount aunt p
A76: 63 | B76: 19 | C76: Ojulu | D76: George | F76: P.1 | G76: 1008817815 | I76: =310000 -> 310000 | K76: =310000 -> 310000 | L76: =I76+J76-K76 -> 0
A77: 66 | B77: 20 | C77: Bakish | D77: sharif | E77: Golden | F77: P.1 | G77: 100888579 | I77: =290000 -> 290000 | K77: =100000+100000+90000 -> 290000 | L77: =I77+J77-K77 -> 0
B78: 21 | C78: Namubiru | D78: cynthia | E78: Annet | F78: P.1 | I78: =310000 -> 310000 | K78: =200000+110000 -> 310000 | L78: =I78+J78-K78 -> 0 | M78: lunch
B79: 22 | C79: Diego | D79: jjemba | E79: malladona | F79: P.1 | I79: =310000 -> 310000 | K79: =100000+100000+110000 -> 310000 | L79: =I79+J79-K79 -> 0
A80: 34 | B80: 23 | C80: Nanyonjo | D80: blessing | E80: kiwanuka | F80: P.1 | G80: 1008730703 | I80: =200000 -> 200000 | K80: =200000 -> 200000 | L80: =I80+J80-K80 -> 0 | M80: discount
B81: 24 | C81: Dikan Joseph | D81: blessing | E81: Teem | F81: P.1 | I81: =310000+50000 -> 360000 | K81: =200000+160000 -> 360000 | L81: =I81+J81-K81 -> 0
B82: 25 | C82: Mukisa | D82: Joshua | F82: P.1 | I82: 250000 | K82: =200000+50000 -> 250000 | L82: =I82+J82-K82 -> 0
B83: 26 | C83: Ssekajja | D83: Reuben | F83: P.1 | I83: 310000 | K83: =150000+100000+60000 -> 310000 | L83: =I83+J83-K83 -> 0
B84: 27 | C84: Ngoloobe | D84: putin | F84: P.1 | I84: =270000 -> 270000 | K84: =100000+170000 -> 270000 | L84: =I84+J84-K84 -> 0
A85: 76 | B85: 28 | C85: Mayega | D85: Mukiibi | E85: Darren | F85: P.1 | I85: 530000 | K85: =100000+200000+230000 -> 530000 | L85: =I85+J85-K85 -> 0 | M85: plus lunch
B86: 29 | C86: Jerome | D86: Kato | E86: Mugwaanya | F86: P.1 | I86: 280000 | K86: =280000 -> 280000 | L86: =I86+J86-K86 -> 0
B87: 30 | C87: Jethro | D87: Wasswa | E87: Mugwaanya | F87: p.1 | I87: 280000 | K87: =280000 -> 280000 | L87: =I87+J87-K87 -> 0
L88: =I88+J88-K88 -> 0
L89: =I89+J89-K89 -> 0
D91: PRIMARY TWO | I91: ='[1]1st term 2025'!J78 -> 0 | L91: =I91+J91-K91 -> 0
A92: 71 | B92: 1 | C92: Namutamba | E92: Faith | F92: P.2 | G92: 1003372958 | H92: 705716541 | I92: ='[1]1st term 2025'!J82 -> 310000 | K92: =150000+50000+50000 -> 250000 | L92: =I92+J92-K92 -> 60000 | N92: =L101+#REF! -> #REF!
A93: 73 | B93: 2 | C93: Kiyimba | E93: Jotham | F93: P.2 | G93: 1003172778 | H93: 776727575 | I93: ='[1]1st term 2025'!J84 -> 310000 | K93: =200000+110000 -> 310000 | L93: =I93+J93-K93 -> 0 | M93: nakyanzi | N93: 320000
A94: 74 | B94: 3 | C94: Bajjampola | E94: Hillary | F94: P.2 | G94: 1006597116 | I94: ='[1]1st term 2025'!J85 -> 310000 | K94: =200000+110000 -> 310000 | L94: =I94+J94-K94 -> 0 | M94: plus lunch
A95: 75 | B95: 4 | C95: Omarimungu | E95: Jordan | F95: P.2 | G95: 1006613689 | I95: 0 | L95: =I95+J95-K95 -> 0 | M95: plus lunch | N95: otm
A96: 78 | B96: 5 | C96: Hannah | D96: isah | E96: Mbowa | F96: P.2 | G96: 1005532248 | I96: ='[1]1st term 2025'!J89 -> 310000 | K96: =100000+100000 -> 200000 | L96: =I96+J96-K96 -> 110000
A97: 79 | B97: 6 | C97: Nambi | E97: Esther | F97: P.2 | G97: 1004773962 | H97: 782025680 | I97: ='[1]1st term 2025'!J90 -> 310000 | K97: =250000+60000 -> 310000 | L97: =I97+J97-K97 -> 0 | M97: harmony
A98: 83 | B98: 7 | C98: Edgar | D98: Ekwap | E98: Barrack | F98: P.2 | G98: 1008697259 | I98: ='[1]1st term 2025'!J94 -> 310000 | K98: =100000+100000+110000 -> 310000 | L98: =I98+J98-K98 -> 0
A99: 84 | B99: 8 | C99: Nalubega | D99: Kim | E99: Keiley | F99: P.2 | G99: 1008713245 | I99: ='[1]1st term 2025'!J95 -> 310000 | K99: =150000+150000+10000 -> 310000 | L99: =I99+J99-K99 -> 0
A100: 85 | B100: 9 | C100: Nakalyango | E100: Shanitah | F100: P.2 | G100: 1008849945 | I100: =290000 -> 290000 | K100: =290000 -> 290000 | L100: =I100+J100-K100 -> 0 | M100: discount
A101: 87 | B101: 10 | C101: Namuwaya | D101: Mitchel | F101: P.2 | G101: 1008878445 | I101: ='[1]1st term 2025'!J98 -> 80000 | K101: =80000 -> 80000 | L101: =I101+J101-K101 -> 0
...

Sheet daily expense
A1: monthly expense per term
A2: item | B2: month | C2: quantity | D2: total | H2: income | I2: otm | J2: fees
A3: food | B3: 3200000 | C3: 3 | D3: =B3*C3 -> 9600000 | I3: 20000000 | J3: 45000000 | K3: =SUM(I3:J3) -> 65000000
A4: ingriendents | B4: 500000 | C4: 3 | D4: =B4*C4 -> 1500000
A5: tr special | B5: 120000 | C5: 3 | D5: =B5*C5 -> 360000
A6: boarding special meal | B6: 60000 | C6: 3 | D6: =B6*C6 -> 180000
A7: payee | B7: 460000 | C7: 3 | D7: =B7*C7 -> 1380000
A8: payee | B8: 110000 | C8: 1 | D8: =B8*C8 -> 110000 | H8: diff
A9: NSSF | B9: 1070000 | C9: 3 | D9: =B9*C9 -> 3210000
A10: NSSF | B10: 870000 | C10: 1 | D10: =B10*C10 -> 870000
A11: salaries | B11: 32163500 | C11: 1 | D11: =B11*C11 -> 32163500
A12: wages | B12: 200000 | C12: 3 | D12: =B12*C12 -> 600000
A13: firewood | B13: 500000 | C13: 3 | D13: =B13*C13 -> 1500000
A14: Electricity | B14: 1000000 | C14: 1 | D14: =B14*C14 -> 1000000
A15: Exams | B15: 660000 | C15: 1 | D15: =B15*C15 -> 660000
A16: mock | B16: 150000 | C16: 1 | D16: =B16*C16 -> 150000
A17: escorts staff | B17: 801500 | C17: 1 | D17: =B17*C17 -> 801500
A18: slashing | B18: 100000 | C18: 3 | D18: =B18*C18 -> 300000
A19: internet | B19: 150000 | C19: 3 | D19: =B19*C19 -> 450000
A20: airtime | B20: 50000 | C20: 3 | D20: =B20*C20 -> 150000
... A27: fuel | B27: 480000 | C27: 3 | D27: =B27*C27 -> 1440000
D28: =B28*C28 -> 0
D29: =B29*C29 -> 0
D30: =SUM(D3:D29) -> 66805000

Sheet school enrollment
A1: OFF-TU EDUCATION CENTRE MUKONO 2026
A2: TERM ONE ENROLLMENT 2026 | E2: TERM TWO ENROLLMENT 2026 | I2: TERM THREE ENROLLMENT 2026
B3: BOYS | C3: GIRLS | D3: TOTAL | F3: BOYS | G3: GIRLS | H3: TOTAL | J3: BOYS | K3: GIRLS | L3: TOTAL
A4: BABY | B4: 7 | C4: 7 | D4: =SUM(B4+C4) -> 14 | E4: BABY | F4: 8 | G4: 7 | H4: =SUM(F4+G4) -> 15 | I4: BABY
A5: MIDDLE | B5: 5 | C5: 8 | D5: =SUM(B5+C5) -> 13 | E5: MIDDLE | F5: 7 | G5: 7 | H5: =SUM(F5+G5) -> 14 | I5: MIDDLE
A6: TOP | B6: 7 | C6: 12 | D6: =SUM(B6+C6) -> 19 | E6: TOP | F6: 10 | G6: 11 | H6: =SUM(F6+G6) -> 21 | I6: TOP
A7: P.1 | B7: 20 | C7: 10 | D7: =SUM(B7+C7) -> 30 | E7: P.1 | F7: 16 | G7: 10 | H7: =SUM(F7+G7) -> 26 | I7: P.1
A8: P.2 | B8: 7 | C8: 9 | D8: =SUM(B8+C8) -> 16 | E8: P.2 | F8: 8 | G8: 13 | H8: =SUM(F8+G8) -> 21 | I8: P.2
A9: P.3 | B9: 10 | C9: 16 | D9: =SUM(B9+C9) -> 26 | E9: P.3 | F9: 9 | G9: 16 | H9: =SUM(F9+G9) -> 25 | I9: P.3
A10: P.4 | B10: 6 | C10: 14 | D10: =SUM(B10+C10) -> 20 | E10: P.4 | F10: 4 | G10: 14 | H10: =SUM(F10+G10) -> 18 | I10: P.4
A11: P.5 | B11: 10 | C11: 14 | D11: =SUM(B11+C11) -> 24 | E11: P.5 | F11: 10 | G11: 15 | H11: =SUM(F11+G11) -> 25 | I11: P.5
A12: P.6 | B12: 12 | C12: 8 | D12: =SUM(B12+C12) -> 20 | E12: P.6 | F12: 14 | G12: 7 | H12: =SUM(F12+G12) -> 21 | I12: P.6
A13: P.7 | B13: 12 | C13: 17 | D13: =SUM(B13+C13) -> 29 | E13: P.7 | F13: 14 | G13: 17 | H13: =SUM(F13+G13) -> 31 | I13: P.7
A14: TOTAL. NO | B14: =SUM(B4:B13) -> 96 | C14: =SUM(C4:C13) -> 115 | D14: =SUM(D4:D13) -> 211 | E14: TOTAL. NO | F14: =SUM(F4:F13) -> 100 | G14: =SUM(G4:G13) -> 117 | H14: =SUM(H4:H13) -> 217 | I14: TOTAL. NO
A16: OTEC TEACHERS ENROLLMENT
A17: MALE | B17: FEMALE | C17: TOTAL
A18: 4 | B18: 10 | C18: 14
A19: NURSERY | B19: LOWER | C19: UPPER
A20: 4 | B20: 6 | C20: 4

Sheet workbooks
D1: total | E1: no of books | F1: price | G1: total | H1: difference | I1: tt px | J1: sch px
A2: P.4 | B2: 6 | C2: 14 | D2: =SUM(B2+C2) -> 20 | E2: 5 | F2: 7000 | G2: =F2*E2 -> 35000 | H2: =J2-I2 -> 500000 | I2: =G2*D2 -> 700000 | J2: =D2*60000 -> 1200000
A3: P.5 | B3: 10 | C3: 14 | D3: =SUM(B3+C3) -> 24 | E3: 5 | F3: 7000 | G3: =F3*E3 -> 35000 | H3: =J3-I3 -> 600000 | I3: =G3*D3 -> 840000 | J3: =D3*60000 -> 1440000
A4: P.6 | B4: 12 | C4: 8 | D4: =SUM(B4+C4) -> 20 | E4: 5 | F4: 7000 | G4: =F4*E4 -> 35000 | H4: =J4-I4 -> 500000 | I4: =G4*D4 -> 700000 | J4: =D4*60000 -> 1200000
A5: P.7 | B5: 12 | C5: 17 | D5: =SUM(B5+C5) -> 29 | E5: 5 | F5: 7000 | G5: =F5*E5 -> 35000 | H5: =J5-I5 -> 725000 | I5: =G5*D5 -> 1015000 | J5: =D5*60000 -> 1740000
D7: =SUM(D2:D6) -> 93 | H7: =SUM(H2:H6) -> 2325000 | I7: =SUM(I2:I6) -> 3255000 | J7: =SUM(J2:J6) -> 5580000
B9: hw | C9: =D2*3500 -> 70000 | H9: =H7-C14 -> 1999500
B10: hw | C10: =D3*3500 -> 84000
B11: hw | C11: =D4*3500 -> 70000
B12: hw | C12: =D5*3500 -> 101500
C14: =SUM(C9:C13) -> 325500
C17: =D7*5 -> 465 | D17: =C17*1000 -> 465000 | F17: =30+15+26 -> 71 | G17: =F17*20000 -> 1420000
D22: =D7*20000 -> 1860000
D24: =D22/350000 -> 5.3142857

Sheet work book TERM 2
I1: PRICE OF WORK BOOK | K1: =60000 -> 60000
B2: TERM TWO WORK BOOKS
B3: NAME | C3: CLASS | D3: AMOUNT PAID | E3: BALANCE | F3: COST | G3: PROFIT | I3: CALCULATION
A4: 1 | B4: MUGABO JOSHUA | C4: P,6 | D4: 60000 | E4: =D4-$K$1 -> 0 | F4: 34800 | G4: =D4-F4 -> 25200 | I4: TOTAL | J4: SPENT | K4: =D109 -> 3650000
A5: =A4+1 -> 2 | B5: TOSUMA CHARLES | C5: P.4 | D5: 60000 | E5: =D5-$K$1 -> 0 | F5: 34800 | G5: =D5-F5 -> 25200 | I5: JEROX | J5: =300000 -> 300000
A6: =A5+1 -> 3 | B6: NASSALI ABIGAIL | C6: P.4 | D6: 60000 | E6: =D6-$K$1 -> 0 | F6: 34800 | G6: =D6-F6 -> 25200 | I6: PEACE | J6: 800000
A7: =A6+1 -> 4 | B7: MUGERWA SAMANTHA | C7: P.4 | D7: 60000 | E7: =D7-$K$1 -> 0 | F7: 34800 | G7: =D7-F7 -> 25200 | I7: PEACE | J7: 300000
A8: =A7+1 -> 5 | B8: TWABALYAKI PETER | C8: P.4 | D8: 60000 | E8: =D8-$K$1 -> 0 | F8: 34800 | G8: =D8-F8 -> 25200 | I8: PEACE | J8: 294400
A9: =A8+1 -> 6 | B9: RUKUNDO SHERINA | C9: P.4 | D9: 60000 | E9: =D9-$K$1 -> 0 | F9: 34800 | G9: =D9-F9 -> 25200 | I9: PEACE | J9: 60000
A10: =A9+1 -> 7 | B10: KYEYUNE GENESIS | C10: P.4 | D10: 60000 | E10: =D10-$K$1 -> 0 | F10: 34800 | G10: =D10-F10 -> 25200 | I10: SPIRO | J10: 1000000
A11: =A10+1 -> 8 | B11: AMODING DESTINY | C11: P.4 | D11: 60000 | E11: =D11-$K$1 -> 0 | F11: 34800 | G11: =D11-F11 -> 25200 | I11: INCOME DAY | J11: 476000
A12: =A11+1 -> 9 | B12: KASOWOLE HAIRAT | C12: P.5 | D12: 60000 | E12: =D12-$K$1 -> 0 | F12: 34800 | G12: =D12-F12 -> 25200
A13: =A12+1 -> 10 | B13: DDAMBA CALVIN | C13: P.5 | D13: 60000 | E13: =D13-$K$1 -> 0 | F13: 34800 | G13: =D13-F13 -> 25200
A14: =A13+1 -> 11 | B14: NANSUBUGA PRETTY | C14: P.5 | D14: 50000 | E14: =D14-$K$1 -> -10000 | F14: 34800 | G14: =D14-F14 -> 15200 | H14: SYS 10K
A15: =A14+1 -> 12 | B15: OMU BENJAMIN | C15: P.5 | D15: 60000 | E15: =D15-$K$1 -> 0 | F15: 34800 | G15: =D15-F15 -> 25200
A16: =A15+1 -> 13 | B16: MARAKA RUBI | C16: P.5 | D16: =30000+30000 -> 60000 | E16: =D16-$K$1 -> 0 | F16: 34800 | G16: =D16-F16 -> 25200
A17: =A16+1 -> 14 | B17: SSEMAKULA ALEYSHA | C17: P.5 | D17: 60000 | E17: =D17-$K$1 -> 0 | F17: 34800 | G17: =D17-F17 -> 25200
A18: =A17+1 -> 15 | B18: ISANKA FRANK | C18: P.5 | D18: 50000 | E18: =D18-$K$1 -> -10000 | F18: 34800 | G18: =D18-F18 -> 15200
A19: =A18+1 -> 16 | B19: BUGWATA HANNAH | C19: P.5 | D19: 60000 | E19: =D19-$K$1 -> 0 | F19: 34800 | G19: =D19-F19 -> 25200 | I19: TOTAL | J19: =SUM(J5:J18) -> 3230400
A20: =A19+1 -> 17 | B20: MEMBE SAMUEL | C20: P.5 | D20: 60000 | E20: =D20-$K$1 -> 0 | F20: 34800 | G20: =D20-F20 -> 25200 | I20: AVAILABLE | K20: =K4-J19 -> 419600
A21: =A20+1 -> 18 | B21: WAIRIMU OKIDI | C21: P.5 | D21: 30000 | E21: =D21-$K$1 -> -30000 | F21: 34800 | G21: =D21-F21 -> -4800
A22: =A21+1 -> 19 | B22: SHILLAH KAANA | C22: P.5 | D22: 60000 | E22: =D22-$K$1 -> 0 | F22: 34800 | G22: =D22-F22 -> 25200
A23: =A22+1 -> 20 | B23: NAMUGABI NISHA | C23: P.5 | D23: =30000+30000 -> 60000 | E23: =D23-$K$1 -> 0 | F23: 34800 | G23: =D23-F23 -> 25200
A24: =A23+1 -> 21 | B24: BIRUNGI PATIENCE | C24: P.5 | D24: 60000 | E24: =D24-$K$1 -> 0 | F24: 34800 | G24: =D24-F24 -> 25200
A25: =A24+1 -> 22 | B25: LWANGA AKRAM | C25: P.5 | D25: 60000 | E25: =D25-$K$1 -> 0 | F25: 34800 | G25: =D25-F25 -> 25200
A26: =A25+1 -> 23 | B26: MUKISA DESTINY | C26: P.5 | D26: 60000 | E26: =D26-$K$1 -> 0 | F26: 34800 | G26: =D26-F26 -> 25200
A27: =A26+1 -> 24 | B27: KATO MATOVU | C27: P.5 | D27: 60000 | E27: =D27-$K$1 -> 0 | F27: 34800 | G27: =D27-F27 -> 25200
A28: =A27+1 -> 25 | B28: WASSWA NSAMBA | C28: P.5 | D28: 60000 | E28: =D28-$K$1 -> 0 | F28: 34800 | G28: =D28-F28 -> 25200
A29: =A28+1 -> 26 | B29: NAMAGANDA PROSSY | C29: P.5 | D29: 60000 | E29: =D29-$K$1 -> 0 | F29: 34800 | G29: =D29-F29 -> 25200
A30: =A29+1 -> 27 | B30: KIRABO ANGEL | C30: P.5 | D30: 60000 | E30: =D30-$K$1 -> 0 | F30: 34800 | G30: =D30-F30 -> 25200
A31: =A30+1 -> 28 | B31: KYESSWA RONALD | C31: P.5 | D31: 60000 | E31: =D31-$K$1 -> 0 | F31: 34800 | G31: =D31-F31 -> 25200
A32: =A31+1 -> 29 | B32: KANSAZE GLORIA | C32: P.6 | D32: 60000 | E32: =D32-$K$1 -> 0 | F32: 34800 | G32: =D32-F32 -> 25200
A33: =A32+1 -> 30 | B33: KAYABULA CHRISTIAN | C33: P.6 | D33: 60000 | E33: =D33-$K$1 -> 0 | F33: 34800 | G33: =D33-F33 -> 25200
A34: =A33+1 -> 31 | B34: NABUTONO ALPHINE | C34: P.6 | D34: 60000 | E34: =D34-$K$1 -> 0 | F34: 34800 | G34: =D34-F34 -> 25200
A35: =A34+1 -> 32 | B35: BAHATI HUMPHREY | C35: P.6 | D35: 60000 | E35: =D35-$K$1 -> 0 | F35: 34800 | G35: =D35-F35 -> 25200
... A49: =A48+1 -> 46 | B49: NAMAGANDA VANESSA | C49: P.7 | D49: 40000 | E49: =D49-$K$1 -> -20000 | F49: 26000 | G49: =D49-F49 -> 14000
A50: =A49+1 -> 47 | B50: ATUHIRWE ALVIN | C50: P.7 | D50: 60000 | E50: =D50-$K$1 -> 0 | F50: 26000 | G50: =D50-F50 -> 34000 | M50: \
A51: =A50+1 -> 48 | B51: OKIRREAGAN | C51: P.7 | D51: 60000 | E51: =D51-$K$1 -> 0 | F51: 26000 | G51: =D51-F51 -> 34000
A52: =A51+1 -> 49 | B52: TUMUKUNDE ARNOLD | C52: P.7 | D52: 60000 | E52: =D52-$K$1 -> 0 | F52: 26000 | G52: =D52-F52 -> 34000
A53: =A52+1 -> 50 | B53: KOBUSINGYE ANITAH | C53: P.7 | D53: 60000 | E53: =D53-$K$1 -> 0 | F53: 26000 | G53: =D53-F53 -> 34000
A54: =A53+1 -> 51 | B54: MUWUMBA PIUS | C54: P.7 | D54: 60000 | E54: =D54-$K$1 -> 0 | F54: 26000 | G54: =D54-F54 -> 34000
A55: =A54+1 -> 52 | B55: MARAKA TAMARA | C55: P.7 | D55: 60000 | E55: =D55-$K$1 -> 0 | F55: 26000 | G55: =D55-F55 -> 34000
A56: =A55+1 -> 53 | B56: BBUMBA GERALD | C56: P.7 | D56: 60000 | E56: =D56-$K$1 -> 0 | F56: 26000 | G56: =D56-F56 -> 34000
A57: =A56+1 -> 54 | B57: MABONGA ASHIM | C57: P.7 | D57: 60000 | E57: =D57-$K$1 -> 0 | F57: 26000 | G57: =D57-F57 -> 34000
A58: =A57+1 -> 55 | B58: OTM GA | D58: 60000 | E58: =D58-$K$1 -> 0 | F58: 34800 | G58: =D58-F58 -> 25200
A59: =A58+1 -> 56 | B59: OTM GA | D59: 60000 | E59: =D59-$K$1 -> 0 | F59: 34800 | G59: =D59-F59 -> 25200
A60: =A59+1 -> 57 | B60: NYONYINTONO RAAIZ | D60: 60000 | E60: =D60-$K$1 -> 0 | F60: 34800 | G60: =D60-F60 -> 25200
B61: BABIRYE JANET MERCY | C61: P.4 | D61: 60000 | E61: =D61-$K$1 -> 0
B62: NAMATTA FAITH | D62: 60000 | E62: =D62-$K$1 -> 0
B63: NABAKIIBI ANGEL | C63: P.5 | D63: 60000
B64: ATAYI VIVIAN | C64: P4 | D64: 60000
B65: KUTEESA JOYCE | C65: P.4 | D65: 60000
B66: PHYLANDER AMARIA | C66: P.7 | D66: 60000
D109: =SUM(D4:D108) -> 3650000 | E109: =SUM(E4:E108) -> -130000 | F109: =SUM(F4:F108) -> 1860400 | G109: =SUM(G4:G108) -> 1429600
D111: SPENT | E111: =300000 -> 300000
E112: 300000
E113: 800000
E114: 294400
E115: 60000
E117: =SUM(E111:E116) -> 1754400
E119: =D109-E117 -> 1895600
D155: =SUM(D4:D154) -> 7300000 | E155: =SUM(E4:E154) -> 5144400 | F155: =SUM(F4:F154) -> 3720800

Sheet library
I1: PRICE OF WORK BOOK | J1: LIB FEE | K1: 20000
B2: TERM TWO WORK BOOKS
B3: NAME | C3: CLASS | D3: AMOUNT PAID | E3: BALANCE | F3: COST | G3: PROFIT | I3: CALCULATION
A4: 1 | B4: KASOWOLE HAIRAT | C4: P.5 | D4: 20000 | I4: TOTAL | K4: =D109 -> 1740000
A5: =A4+1 -> 2 | B5: NAKAWUNDE CELLINE | C5: P.7 | D5: 20000 | I5: SPENT
A6: =A5+1 -> 3 | B6: DDAMBA CALVIN | C6: P.5 | D6: 20000 | I6: PRINTER | J6: 700000
A7: =A6+1 -> 4 | B7: NAMAGANDA VANESSA | C7: P.7 | D7: 20000 | I7: 2 COMPUTERS | J7: 800000
A8: =A7+1 -> 5 | B8: SSEKAJJA REUBEN | C8: P.1 | D8: 20000 | I8: GRAVEL | J8: 70000
A9: =A8+1 -> 6 | B9: NAMBUYA MALIKAH | C9: P.1 | D9: 20000 | I9: YAKA | J9: 150000
A10: =A9+1 -> 7 | B10: NYONYINTONO RAAIZ | C10: P.5 | D10: 20000
A11: =A10+1 -> 8 | B11: TOSUMA CHARLES | C11: P.4 | D11: 20000
A12: =A11+1 -> 9 | B12: NAMBI ESTHER | C12: P.2 | D12: 20000
A13: =A12+1 -> 10 | B13: KWAGALAKWE MELLISA | C13: P.3 | D13: 20000
A14: =A13+1 -> 11 | B14: FAUDEL NAJIB | C14: P.1 | D14: 20000
A15: =A14+1 -> 12 | B15: OMU BENJAMIN | C15: P.5 | D15: 20000
A16: =A15+1 -> 13 | B16: NASSALI ABIGAIL | C16: P.4 | D16: 20000
A17: =A16+1 -> 14 | B17: MUGERWA SAMANTHA | C17: P.4 | D17: 20000
A18: =A17+1 -> 15 | B18: WESONGA EMMANUEL | C18: MIDDLE | D18: 20000
A19: =A18+1 -> 16 | B19: SSEMAKULA ALEYSHA | C19: P.5 | D19: 20000 | I19: TOTAL: | J19: =SUM(J6:J18) -> 1720000
A20: =A19+1 -> 17 | B20: KISAKYE JOSHUA | C20: P.6 | D20: 20000 | I20: AVAILABLE | K20: =K4-J19 -> 20000
A21: =A20+1 -> 18 | B21: TUMUKUNDE ARNOLD | C21: P.7 | D21: 20000
A22: =A21+1 -> 19 | B22: KOBUSINGYE ANITAH | C22: P.7 | D22: 20000
A23: =A22+1 -> 20 | B23: SSEMAKULA WILSON | C23: P.6 | D23: 20000
A24: =A23+1 -> 21 | B24: TUSHEMEREIRWE ADRINE | C24: P.7 | D24: 20000
A25: =A24+1 -> 22 | B25: NABUTONO ALPHINE | C25: P.6 | D25: 20000
A26: =A25+1 -> 23 | B26: KUGUMA KEVIN | C26: P.6 | D26: 20000
A27: =A26+1 -> 24 | B27: BAHATI HUMPHREY | C27: P.6 | D27: 20000
A28: =A27+1 -> 25 | B28: ACHADU SERENA | C28: P.1 | D28: 20000
A29: =A28+1 -> 26 | B29: EKWAP EDGER | C29: P.2 | D29: 20000
A30: =A29+1 -> 27 | B30: MUKISA JEREMIAH | C30: P.1 | D30: 20000
A31: =A30+1 -> 28 | B31: MUKISA NATHANIEL | C31: P.1 | D31: 20000
A32: =A31+1 -> 29 | B32: LWANGA DESTINY | C32: P.1 | D32: 20000
... A57: =A56+1 -> 54 | B57: NAKAZIBWE DESIRE | C57: P.7 | D57: 20000
A58: =A57+1 -> 55 | B58: OTM GA | D58: 20000
A59: =A58+1 -> 56 | B59: OTM GA | D59: 20000
A60: =A59+1 -> 57 | B60: NAMBOOZO EMMANUEL | C60: P.1 | D60: 20000
A61: =A60+1 -> 58 | B61: MIREMBE ZURI | C61: P.1 | D61: 20000
A62: =A61+1 -> 59 | B62: MUKISA NATHANIEL | C62: P.1 | D62: 20000 | O62: 1
A63: =A62+1 -> 60 | B63: NITE KAWALA | C63: P.2 | D63: 20000
A64: =A63+1 -> 61 | B64: ADRINE TUSHEMEREIRWE | C64: P.3 | D64: 20000
A65: =A64+1 -> 62 | B65: NAIGA SHEILLAH | C65: P.3 | D65: 20000
A66: =A65+1 -> 63 | B66: NAMAGANDA MELISA | C66: P.3 | D66: 20000
A67: =A66+1 -> 64 | B67: RUKUNDO SHERINA | C67: P.4 | D67: 20000
A68: =A67+1 -> 65 | B68: HANNAH BUGWATA | C68: P.5 | D68: 20000
A69: =A68+1 -> 66 | B69: NAMAGANDA PROSSY | C69: P.5 | D69: 20000
A70: =A69+1 -> 67 | B70: WASSWA DENIS | C70: P.5 | D70: 20000
A71: =A70+1 -> 68 | B71: MATOVU DOUGLAS | C71: P.5 | D71: 20000
A72: =A71+1 -> 69 | B72: ASHIM MABONGA | C72: P.7 | D72: 20000
A73: =A72+1 -> 70 | B73: NAMUTEBI SARAH | C73: P.1 | D73: 20000
A74: =A73+1 -> 71 | B74: TWABALYAKI PETER | C74: P.4 | D74: 20000
... A90: =A89+1 -> 87 | B90: DIKAN BLESSING | C90: P.1 | D90: 20000
A91: =A90+1 -> 88
A92: =A91+1 -> 89
A93: =A92+1 -> 90
A94: =A93+1 -> 91
A95: =A94+1 -> 92
A96: =A95+1 -> 93
A97: =A96+1 -> 94
A98: =A97+1 -> 95
A99: =A98+1 -> 96
A100: =A99+1 -> 97
A101: =A100+1 -> 98
A102: =A101+1 -> 99
... A107: =A106+1 -> 104
D109: =SUM(D4:D108) -> 1740000
E117: =SUM(E111:E116) -> 0
E119: =D109-E117 -> 1740000

Sheet UNIFORMS TERM TWO
A1: UNIFORMS TERM TWO
A2: DATE | B2: ITEM | C2: RECEIVED | D2: REFUND | E2: SPENT | F2: BALANCE

Sheet term two fees
B1: SI No. | C1: First Name | D1: Middle Name | E1: Last Name | F1: Class Code | G1: Payment Code | H1: Guardian Phone | I1: fees due | J1: outstanding | K1: amount paid | L1: balance | M1: category | N1: colour category | O1: debt carried forward
A2: 1 | B2: 1 | C2: Aleem | D2: Galugali | E2: Afan | F2: ELEPHANT | G2: 1010521012 | I2: 290000 | J2: ='term one 2026'!L2 -> 0 | K2: =100000+150000+40000 -> 290000 | L2: =I2+J2-K2 -> 0
A3: 2 | B3: 2 | C3: Mugambwa | D3: tyrone Tendo | E3: Mukasa | F3: ELEPHANT | G3: 1010607442 | I3: 290000 | J3: ='term one 2026'!L3 -> 0 | K3: =200000+90000 -> 290000 | L3: =I3+J3-K3 -> 0
A4: 3 | B4: 3 | C4: Nikky | D4: Nansubuga | F4: ELEPHANT | G4: 1010668240 | I4: 200000 | J4: ='term one 2026'!L4 -> 0 | K4: =100000+50000+50000 -> 200000 | L4: =I4+J4-K4 -> 0
A5: 4 | B5: 4 | C5: Nabatanzi | D5: Bint Hamis | E5: Hannah | F5: ELEPHANT | G5: 1010680309 | I5: 270000 | J5: ='term one 2026'!L5 -> 0 | K5: =200000+70000 -> 270000 | L5: =I5+J5-K5 -> 0
A6: 5 | B6: 5 | C6: Sempela | D6: Paul | E6: Troy | F6: ELEPHANT | I6: =290000+300000 -> 590000 | J6: ='term one 2026'!L6 -> 0 | K6: =590000 -> 590000 | L6: =I6+J6-K6 -> 0
A7: 6 | B7: 6 | C7: Ruth | D7: Mirab | F7: ELEPHANT | I7: =200000 -> 200000 | J7: ='term one 2026'!L7 -> 0 | K7: =200000 -> 200000
A8: 7 | B8: 7 | C8: Nimurungi | D8: Alvin | E8: Sserugo | F8: ELEPHANT | I8: 80000 | J8: ='term one 2026'!L8 -> 0 | L8: =I8+J8-K8 -> 80000
A9: 8 | B9: 8 | C9: Nalubega | D9: Samantha | E9: Zion | F9: ELEPHANT | I9: 80000 | J9: ='term one 2026'!L9 -> 40000 | L9: =I9+J9-K9 -> 120000
A10: 9 | B10: 9 | C10: Nanyonga | D10: Pretty | E10: kiwanuka | F10: ELEPHANT | I10: 200000 | J10: ='term one 2026'!L10 -> 0 | K10: =200000 -> 200000 | L10: =I10+J10-K10 -> 0
A11: 10 | B11: 10 | C11: Adeke | D11: Dinah | F11: ELEPHANT | I11: 290000 | J11: ='term one 2026'!L11 -> 0 | K11: =290000 -> 290000 | L11: =I11+J11-K11 -> 0
A12: 11 | B12: 11 | C12: Namutebi | D12: Shukran | F12: ELEPHANT | I12: =260000 -> 260000 | J12: ='term one 2026'!L12 -> 0 | K12: =100000 -> 100000 | L12: =I12+J12-K12 -> 160000 | M12: discount | N12: ream
A13: 12 | B13: 12 | C13: Mukisa | D13: Daniel | F13: ELEPHANT | I13: =290000+250000 -> 540000 | J13: ='term one 2026'!L13 -> 0 | K13: =540000 -> 540000 | L13: =I13+J13-K13 -> 0
A14: 13 | B14: 13 | C14: Wesonga | D14: Emmanuel | F14: ZEBRA | I14: =260000+100000 -> 360000 | J14: ='term one 2026'!L14 -> 60000 | K14: =100000+130000 -> 230000 | L14: =I14+J14-K14 -> 190000 | M14: vau user | N14: 260000
A15: 14 | B15: 14 | C15: Aafruuz | D15: Mutambuli | E15: Mansoor | F15: ELEPHANT | I15: 250000 | J15: ='term one 2026'!L15 -> 0 | K15: =100000 -> 100000 | L15: =I15+J15-K15 -> 150000
A16: 15 | B16: 15 | C16: Mali | D16: Gracious | F16: ELEPHANT | I16: 80000 | J16: ='term one 2026'!L16 -> 0 | L16: =I16+J16-K16 -> 80000
F17: ELEPHANT | J17: ='term one 2026'!L18 -> 0 | L17: =I17+J17-K17 -> 0
F18: ELEPHANT | J18: ='term one 2026'!L19 -> 0 | L18: =I18+J18-K18 -> 0
F19: ELEPHANT | J19: ='term one 2026'!L20 -> 0 | L19: =I19+J19-K19 -> 0
F20: ELEPHANT | J20: ='term one 2026'!L21 -> 0 | L20: =I20+J20-K20 -> 0
D21: ZEBRA | I21: 0 | J21: ='term one 2026'!L22 -> 0 | L21: =I21+J21-K21 -> 0
A22: 16 | B22: 1 | C22: Nansubuga | E22: Shuquran | F22: ZEBRA | G22: 1008799582 | I22: =290000 -> 290000 | J22: ='term one 2026'!L23 -> 0 | K22: =115000+50000+50000+40000+15000+20000 -> 290000 | L22: =I22+J22-K22 -> 0
A23: 17 | B23: 2 | C23: Wamala | E23: Abdu | F23: ZEBRA | G23: 1008807850 | I23: =290000 -> 290000 | J23: ='term one 2026'!L24 -> 1000 | K23: =101000+50000+59000 -> 210000 | L23: =I23+J23-K23 -> 81000
A24: 18 | B24: 3 | C24: Namwori | E24: Grace | F24: ZEBRA | G24: 1008878539 | I24: ='[1]1st term 2025'!J8 -> 80000 | J24: ='term one 2026'!L25 -> 0 | K24: =80000 -> 80000 | L24: =I24+J24-K24 -> 0 | M24: teachers child
A25: 19 | B25: 4 | C25: ivana | D25: Namutebi | F25: ZEBRA | I25: ='[1]1st term 2025'!J11 -> 80000 | J25: ='term one 2026'!L27 -> 0 | K25: =10000+50000 -> 60000 | L25: =I25+J25-K25 -> 20000 | M25: cook
A26: 20 | B26: 5 | C26: Ssenyondo | D26: Biden | E26: kakooza jovan | F26: ZEBRA | G26: 1009022251 | I26: =260000 -> 260000 | J26: ='term one 2026'!L28 -> 90000 | K26: =150000+100000+50000 -> 300000 | L26: =I26+J26-K26 -> 50000 | M26: ream
A27: 21 | B27: 6 | C27: Nakitende | D27: mercy | E27: Elizabeth | F27: ZEBRA | G27: 1008940427 | I27: =290000 -> 290000 | J27: ='term one 2026'!L29 -> -100000 | K27: =150000+40000 -> 190000 | L27: =I27+J27-K27 -> 0
A28: 22 | B28: 7 | C28: Muwanguzi | D28: Lael | E28: victor | F28: ZEBRA | G28: 1009102896 | I28: ='[1]1st term 2025'!J17+30000 -> 290000 | J28: ='term one 2026'!L30 -> 0 | K28: =290000 -> 290000 | L28: =I28+J28-K28 -> 0
A29: 23 | B29: 8 | C29: Gabriell | D29: Ayerango | E29: Grace | F29: ZEBRA | G29: 1009426740 | I29: =290000+60000+60000 -> 410000 | J29: ='term one 2026'!L31 -> 0 | K29: =130000+100000+180000 -> 410000 | L29: =I29+J29-K29 -> 0 | M29: reported in march
A30: 24 | B30: 9 | C30: Mulwanyi | E30: Chrizestom | F30: ZEBRA | G30: 1008793531 | I30: =220000 -> 220000 | J30: 0 | K30: =50000+30000 -> 80000 | L30: =I30+J30-K30 -> 140000
A31: 25 | B31: 10 | C31: Kaleb | D31: Myles | E31: Kolya | F31: ZEBRA | G31: 1009836293 | I31: =260000+30000 -> 290000 | J31: ='term one 2026'!L33 -> 0 | K31: =20000+270000 -> 290000 | L31: =I31+J31-K31 -> 0
A32: 26 | B32: 11 | C32: Princess | D32: Ayinebyona | E32: Nakato | F32: ZEBRA | I32: =260000+30000 -> 290000 | J32: ='term one 2026'!L34 -> 145000 | K32: =80000+100000+35000 -> 215000 | L32: =I32+J32-K32 -> 220000
A33: 27 | B33: 12 | C33: Lauren | D33: Asio | E33: Malaika | F33: ZEBRA | I33: =290000+50000 -> 340000 | J33: ='term one 2026'!L35 -> 0 | K33: =340000 -> 340000 | L33: =I33+J33-K33 -> 0
A34: 28 | B34: 13 | C34: Alvin | D34: Mutebi | F34: ZEBRA | I34: =250000 -> 250000 | J34: ='term one 2026'!L36 -> 0 | K34: =130000+30000+35000+55000 -> 250000 | L34: =I34+J34-K34 -> 0 | M34: escorts
A35: 29 | B35: 14 | C35: Ntambi | D35: Ramos | E35: Kabenge | F35: ZEBRA | I35: =250000+50000 -> 300000 | K35: =100000+50000+150000 -> 300000 | L35: =I35+J35-K35 -> 0
D36: LION | I36: ='[1]1st term 2025'!J23 -> 0 | J36: ='term one 2026'!L37 -> 0 | L36: =I36+J36-K36 -> 0
A37: 30 | B37: 1 | C37: Nakigozi | D37: Brovia | E37: Martha | F37: LION | G37: 1006914417 | I37: ='[1]1st term 2025'!J24 -> 255000 | J37: ='term one 2026'!L38 -> -70000 | K37: =100000+35000+50000 -> 185000 | L37: =I37+J37-K37 -> 0 | M37: f
A38: 31 | B38: 2 | C38: Ssemakula | D38: Joseph | E38: Asher | F38: LION | G38: 1006914745 | I38: ='[1]1st term 2025'!J25+100000 -> 180000 | J38: ='term one 2026'!L39 -> 0 | K38: =180000 -> 180000 | L38: =I38+J38-K38 -> 0 | M38: f
A39: 32 | B39: 3 | C39: Kristian | D39: Pendo | E39: Ogola | F39: LION | G39: 1007134587 | I39: ='[1]1st term 2025'!J27 -> 260000 | J39: ='term one 2026'!L40 -> 0 | K39: =160000+100000 -> 260000 | L39: =I39+J39-K39 -> 0 | M39: f | N39: =L40+L43+#REF!+L44+#REF!+#REF!+#REF! -> #REF!
A40: 33 | B40: 4 | C40: Nakyeyune | D40: Hamnah | E40: Sarah | F40: LION | G40: 1007092280 | I40: ='[1]1st term 2025'!J28 -> 260000 | J40: ='term one 2026'!L41 -> 80000 | K40: =100000+80000+90000 -> 270000 | L40: =I40+J40-K40 -> 70000 | M40: ream
A41: 34 | B41: 5 | C41: Ekisula ebweru | E41: salim | F41: LION | G41: 1007044996 | I41: ='[1]1st term 2025'!J29 -> 290000 | J41: ='term one 2026'!L42 -> 0 | K41: =150000+140000 -> 290000 | L41: =I41+J41-K41 -> 0 | M41: f
A42: 35 | B42: 6 | C42: Babirye | D42: Miracle | E42: Victoria | F42: LION | I42: 0 | J42: 0 | L42: =I42+J42-K42 -> 0 | M42: f | N42: yellow =iccsp
A43: 36 | B43: 7 | C43: Ganiima | D43: Nakkuni | E43: Ramsha | F43: LION | I43: ='[1]1st term 2025'!J32 -> 260000 | J43: ='term one 2026'!L44 -> 0 | K43: =100000+100000+20000 -> 220000 | L43: =I43+J43-K43 -> 40000 | M43: f
A44: 37 | B44: 8 | C44: Kiyimba | E44: Joram | F44: LION | G44: 1005580041 | I44: ='[1]1st term 2025'!J34 -> 230000 | J44: ='term one 2026'!L45 -> 0 | L44: =I44+J44-K44 -> 230000 | M44: nakyanzi f | N44: 274000
A45: 38 | B45: 9 | C45: Mukisa | E45: Sharom | F45: LION | G45: 1007986138 | I45: 0 | J45: ='term one 2026'!L46 -> 0 | L45: =I45+J45-K45 -> 0
A46: 39 | B46: 10 | C46: Saka | E46: Raymond | F46: LION | G46: 1007991074 | I46: ='[1]1st term 2025'!J37+30000 -> 290000 | J46: ='term one 2026'!L47 -> 65000 | K46: =40000+10000+70000+30000+70000+75000 -> 295000 | L46: =I46+J46-K46 -> 60000 | M46: ream
A47: 40 | B47: 11 | C47: Suhairah | E47: Isah | F47: LION | G47: 1008057858 | I47: ='[1]1st term 2025'!J38+30000 -> 290000 | J47: ='term one 2026'!L48 -> 90000 | K47: =200000+100000+80000 -> 380000 | L47: =I47+J47-K47 -> 0 | M47: ream | N47: =SUM(L37+#REF!+L39+L40+L41+#REF!+#REF!+L43+#REF!+L44+#REF!+L46+L47) -> #REF!
A48: 41 | B48: 12 | C48: Mubiru | E48: Fahim | F48: LION | G48: 1008799658 | I48: ='[1]1st term 2025'!J41 -> 260000 | J48: ='term one 2026'!L50 -> 0 | K48: =115000+50000+50000+30000+15000 -> 260000 | L48: =I48+J48-K48 -> 0
A49: 42 | B49: 13 | C49: Hossana | D49: Nakiberu | E49: Abigail | F49: LION | I49: ='[1]1st term 2025'!J43+100000+20000+20000 -> 400000 | J49: ='term one 2026'!L51 -> 0 | K49: =100000+100000+200000 -> 400000 | L49: =I49+J49-K49 -> 0 | M49: ream
A50: 43 | B50: 14 | C50: mudoola | D50: Travis | F50: LION | I50: ='[1]1st term 2025'!J45 -> 80000 | J50: ='term one 2026'!L52 -> 0 | K50: =80000 -> 80000 | L50: =80000 -> 80000
A51: 44 | B51: 15 | C51: Ninsiima | D51: Dyna | F51: LION | G51: 1009792957 | I51: =290000+200000 -> 490000 | J51: ='term one 2026'!L53 -> 0 | K51: =200000+290000 -> 490000 | L51: =I51+J51-K51 -> 0 | M51: van user
A52: 45 | B52: 16 | C52: Namuganyi | D52: kellen | F52: LION | I52: =260000+30000 -> 290000 | J52: 50000 | K52: =150000+100000 -> 250000 | L52: =I52+J52-K52 -> 90000 | M52: ream | N52: 80000
A53: 46 | B53: 17 | C53: Nakibuuka | D53: Mary | F53: LION | I53: =260000+30000 -> 290000 | J53: =90000 -> 90000 | K53: =150000+100000 -> 250000 | L53: =I53+J53-K53 -> 130000 | M53: ream
A54: 47 | B54: 18 | C54: Mirembe | D54: Lois | F54: LION | I54: 80000 | J54: ='term one 2026'!L56 -> 0 | L54: =I54+J54-K54 -> 80000
A55: 48 | B55: 19 | C55: Faudel | D55: Najib | F55: p.1 | I55: 310000 | J55: ='term one 2026'!L88 -> 0 | K55: =100000+110000+100000 -> 310000 | L55: =I55+J55-K55 -> 0
A56: 49 | B56: 20 | C56: Kanamwangi | D56: calvin | F56: lion | I56: 250000 | K56: =150000 -> 150000 | L56: =I56+J56-K56 -> 100000
A57: 50 | B57: 21 | C57: Kaweesa | D57: Gideon | E57: Mukisa | I57: =290000 -> 290000 | K57: =100000+30000+20000+10000+20000 -> 180000 | L57: =I57+J57-K57 -> 110000
F58: PRIMARY ONE
A59: 51 | B59: 1 | C59: Victor | E59: Mugisha | F59: P.1 | G59: 1004598780 | H59: 705362439 | I59: =310000 -> 310000 | J59: ='term one 2026'!L58 -> 195000 | K59: =195000+100000 -> 295000 | L59: =I59+J59-K59 -> 210000 | M59: staff(eva nakalembe) f
A60: 52 | B60: 2 | C60: Emmanuella | D60: Lubega | E60: Namboozo | F60: P.1 | G60: 1004970591 | H60: 706082006 | I60: 100000 | J60: ='term one 2026'!L59 -> 0 | K60: =100000 -> 100000 | L60: =I60+J60-K60 -> 0 | M60: cassava
A61: 53 | B61: 3 | C61: Mirembe | E61: Zuri | F61: P.1 | G61: 1004702849 | H61: 789426721 | I61: 0 | J61: ='term one 2026'!L60 -> 0 | L61: =I61+J61-K61 -> 0 | M61: plus lunch f
A62: 54 | B62: 4 | C62: Jeredin | D62: Kibumba | E62: Bitege | F62: P.1 | G62: 1005019546 | H62: 759659001 | I62: =310000 -> 310000 | J62: ='term one 2026'!L61 -> 60000 | K62: =100000+100000+90000 -> 290000 | L62: =I62+J62-K62 -> 80000 | M62: f
A63: 55 | B63: 5 | C63: Haitham | E63: Kyeyune | F63: P.1 | G63: 1006568232 | I63: =310000 -> 310000 | J63: =80000 -> 80000 | K63: =100000+100000+100000 -> 300000 | L63: =I63+J63-K63 -> 90000 | M63: lunch also inclusive at this amount f
A64: 56 | B64: 6 | C64: kawalya | E64: hormony | F64: P.1 | G64: 1006597691 | I64: =300000 -> 300000 | J64: ='term one 2026'!L63 -> 0 | K64: =100000+100000+100000 -> 300000 | L64: =I64+J64-K64 -> 0 | M64: plus lunch f | N64: =L59+#REF! -> #REF!
A65: 57 | B65: 7 | C65: Lwanga | D65: Destiny | E65: Adrian | F65: P.1 | G65: 1006613640 | I65: 0 | J65: ='term one 2026'!L64 -> 0 | L65: =I65+J65-K65 -> 0 | M65: f | N65: red= otm
A66: 58 | B66: 8 | C66: Jeremiah | E66: Mukisa | F66: P.1 | I66: 0 | J66: ='term one 2026'!L65 -> 0 | L66: =I66+J66-K66 -> 0 | M66: f
A67: 59 | B67: 9 | C67: Gift | E67: nakiwala | F67: P.1 | I67: 0 | J67: ='term one 2026'!L66 -> 0 | L67: =I67+J67-K67 -> 0 | M67: f
A68: 60 | B68: 10 | C68: Kizza | D68: Brian | E68: Bumpenje Prosper | F68: P.1 | G68: 1006973917 | I68: 0 | J68: ='term one 2026'!L68 -> 0 | L68: =I68+J68-K68 -> 0 | M68: f | N68: blue =GA
A69: 61 | B69: 11 | C69: Nakasujja | D69: Ivy | E69: Catherine | F69: P.1 | G69: 1007985992 | I69: =310000 -> 310000 | J69: ='term one 2026'!L69 -> 0 | K69: =200000+110000 -> 310000 | L69: =I69+J69-K69 -> 0
A70: 62 | B70: 12 | C70: Mukisa | E70: Nathaniel | F70: P.1 | G70: 1007986167 | I70: 0 | J70: ='term one 2026'!L70 -> 0 | L70: =I70+J70-K70 -> 0
A71: 63 | B71: 13 | C71: Crystal | D71: Havah | E71: Aturinda | F71: P.1 | G71: 1008016084 | I71: =310000+150000 -> 460000 | J71: ='term one 2026'!L71 -> 0 | K71: =300000+160000 -> 460000 | L71: =I71+J71-K71 -> 0 | N71: =SUM(L59+L62+#REF!+L63+L64+#REF!+#REF!+#REF!+#REF!+L69+#REF!+L71+L72) -> #REF!
A72: 64 | B72: 14 | C72: Kajjubi | D72: Alkham | F72: P.1 | G72: 1008448676 | I72: =310000 -> 310000 | J72: ='term one 2026'!L72 -> 70000 | K72: =50000+150000+80000 -> 280000 | L72: =I72+J72-K72 -> 100000
A73: 65 | B73: 15 | C73: Precious | D73: Maali | E73: evelyne | F73: P.1 | I73: ='[1]1st term 2025'!J67 -> 80000 | J73: ='term one 2026'!L73 -> 0 | K73: =80000 -> 80000 | L73: =I73+J73-K73 -> 0
A74: 66 | B74: 16 | C74: Serena | D74: Achadu | E74: Barrika | F74: P.1 | G74: 1008697299 | I74: =310000+100000 -> 410000 | J74: ='term one 2026'!L74 -> 0 | K74: =100000+150000+160000 -> 410000 | L74: =I74+J74-K74 -> 0 | M74: ekwap and humphrey
A75: 67 | B75: 17 | C75: Latifa | D75: Nambuya | E75: Malika | F75: P.1 | I75: ='[1]1st term 2025'!J69 -> 500000 | J75: ='term one 2026'!L75 -> 0 | K75: =400000+100000 -> 500000 | L75: =I75+J75-K75 -> 0 | M75: discount aunt p
A76: 68 | B76: 18 | C76: Ojulu | D76: George | F76: P.1 | G76: 1008817815 | I76: =310000 -> 310000 | J76: ='term one 2026'!L76 -> 0 | K76: =310000 -> 310000 | L76: =I76+J76-K76 -> 0
A77: 69 | B77: 19 | C77: Nanyonjo | D77: blessing | E77: kiwanuka | F77: P.1 | G77: 1008730703 | I77: =200000 -> 200000 | J77: ='term one 2026'!L80 -> 0 | K77: =200000 -> 200000 | L77: =I77+J77-K77 -> 0 | M77: discount
A78: 70 | B78: 20 | C78: Dikan Joseph | D78: blessing | E78: Teem | F78: P.1 | I78: =310000+50000 -> 360000 | J78: ='term one 2026'!L81 -> 0 | K78: =160000+200000 -> 360000 | L78: =I78+J78-K78 -> 0
A79: 71 | B79: 21 | C79: Ssekajja | D79: Reuben | F79: P.1 | I79: 310000 | J79: ='term one 2026'!L83 -> 0 | K79: =200000+50000+30000 -> 280000 | L79: =I79+J79-K79 -> 30000
A80: 72 | B80: 22 | C80: Ngoloobe | D80: putin | F80: P.1 | I80: =270000 -> 270000 | J80: ='term one 2026'!L84 -> 0 | K80: =70000+100000 -> 170000 | L80: =I80+J80-K80 -> 100000
A81: 73 | B81: 23 | C81: Mayega | D81: Mukiibi | E81: Darren | F81: P.1 | I81: 530000 | J81: ='term one 2026'!L85 -> 0 | K81: =500000+30000 -> 530000 | L81: =I81+J81-K81 -> 0 | M81: plus lunch
A82: 74 | B82: 24 | C82: Jerome | D82: Kato | E82: Mugwaanya | F82: P.1 | I82: =280000+20000 -> 300000 | J82: ='term one 2026'!L86 -> 0 | K82: =100000+50000+50000 -> 200000 | L82: =I82+J82-K82 -> 100000
A83: 75 | B83: 25 | C83: Jethro | D83: Wasswa | E83: Mugwaanya | F83: p.1 | I83: =280000+20000 -> 300000 | J83: ='term one 2026'!L87 -> 0 | K83: =100000+50000+50000 -> 200000 | L83: =I83+J83-K83 -> 100000
A84: 76 | B84: 26 | C84: Namutebi | D84: Sarah | F84: p.1 | I84: =250000 -> 250000 | K84: =100000+100000 -> 200000 | L84: =I84+J84-K84 -> 50000
J85: ='term one 2026'!L89 -> 0 | L85: =I85+J85-K85 -> 0
J86: ='term one 2026'!L90 -> 0
D87: PRIMARY TWO | I87: ='[1]1st term 2025'!J78 -> 0 | J87: ='term one 2026'!L91 -> 0 | L87: =I87+J87-K87 -> 0
A88: 77 | B88: 1 | C88: Namutamba | E88: Faith | F88: P.2 | G88: 1003372958 | H88: 705716541 | I88: ='[1]1st term 2025'!J82 -> 310000 | J88: ='term one 2026'!L92 -> 60000 | K88: =60000 -> 60000 | L88: =I88+J88-K88 -> 310000 | N88: =L97+#REF! -> #REF!
A89: 78 | B89: 2 | C89: Kiyimba | E89: Jotham | F89: P.2 | G89: 1003172778 | H89: 776727575 | I89: ='[1]1st term 2025'!J84 -> 310000 | J89: ='term one 2026'!L93 -> 0 | K89: =200000+50000 -> 250000 | L89: =I89+J89-K89 -> 60000 | M89: nakyanzi | N89: 320000
A90: 79 | B90: 3 | C90: Bajjampola | E90: Hillary | F90: P.2 | G90: 1006597116 | I90: ='[1]1st term 2025'!J85 -> 310000 | J90: ='term one 2026'!L94 -> 0 | K90: =150000+160000 -> 310000 | L90: =I90+J90-K90 -> 0 | M90: plus lunch
A91: 80 | B91: 4 | C91: Omarimungu | E91: Jordan | F91: P.2 | G91: 1006613689 | I91: 0 | J91: ='term one 2026'!L95 -> 0 | L91: =I91+J91-K91 -> 0 | M91: plus lunch | N91: otm
A92: 81 | B92: 5 | C92: Hannah | D92: isah | E92: Mbowa | F92: P.2 | G92: 1005532248 | I92: ='[1]1st term 2025'!J89+20000 -> 330000 | J92: ='term one 2026'!L96 -> 110000 | K92: =200000+100000+100000+40000 -> 440000 | L92: =I92+J92-K92 -> 0
A93: 82 | B93: 6 | C93: Nambi | E93: Esther | F93: P.2 | G93: 1004773962 | H93: 782025680 | I93: ='[1]1st term 2025'!J90 -> 310000 | J93: ='term one 2026'!L97 -> 0 | K93: =230000+80000 -> 310000 | L93: =I93+J93-K93 -> 0 | M93: harmony
A94: 83 | B94: 7 | C94: Edgar | D94: Ekwap | E94: Barrack | F94: P.2 | G94: 1008697259 | I94: ='[1]1st term 2025'!J94+100000 -> 410000 | J94: ='term one 2026'!L98 -> 0 | K94: =100000+150000+160000 -> 410000 | L94: =I94+J94-K94 -> 0
A95: 84 | B95: 8 | C95: Nalubega | D95: Kim | E95: Keiley | F95: P.2 | G95: 1008713245 | I95: ='[1]1st term 2025'!J95 -> 310000 | J95: ='term one 2026'!L99 -> 0 | K95: =50000+50000+200000+60000 -> 360000 | L95: =I95+J95-K95 -> -50000
A96: 85 | B96: 9 | C96: Nakalyango | E96: Shanitah | F96: P.2 | G96: 1008849945 | I96: =290000 -> 290000 | J96: ='term one 2026'!L100 -> 0 | K96: =290000 -> 290000 | L96: =I96+J96-K96 -> 0 | M96: discount
A97: 86 | B97: 10 | C97: Namuwaya | D97: Mitchel | F97: P.2 | G97: 1008878445 | I97: ='[1]1st term 2025'!J98 -> 80000 | J97: ='term one 2026'!L101 -> 0 | K97: =80000 -> 80000 | L97: =I97+J97-K97 -> 0
A98: 87 | B98: 11 | C98: Karungi | D98: Lewin | E98: Amber | F98: P.2 | G98: 100888661 | I98: ='[1]1st term 2025'!J99+20000 -> 280000 | J98: ='term one 2026'!L102 -> 0 | K98: =150000 -> 150000 | L98: =I98+J98-K98 -> 130000
A99: 88 | B99: 12 | C99: Achsah | D99: Naava | E99: Serah | F99: P.2 | G99: 1008894881 | I99: =300000+100000 -> 400000 | J99: ='term one 2026'!L103 -> 0 | K99: =100000+100000 -> 200000 | L99: =I99+J99-K99 -> 200000
A100: 89 | B100: 13 | C100: Kadyesi | E100: Muhammad | F100: P.2 | G100: 1008984556 | I100: ='[1]1st term 2025'!J102 -> 400000 | J100: ='term one 2026'!L105 -> 0 | K100: =300000+100000 -> 400000 | L100: =I100+J100-K100 -> 0 | M100: van user
...

Sheet Sheet1
